{
    "metaDataVersion": "1.0.0",
    "category": "com.microchip.ide.project",
    "content": {
        "metaDataVersion": "1.1.0",
        "name": "com.microchip.mcu8.mplabx.project.pic18f16q41-cnano-opamp-demo-fw",
        "version": "1.0.0",
        "displayName": "PIC18F16Q41 Curiosity Nano OPA Demo Firmware",
        "projectName": "pic18f16q41-cnano-opamp-demo-fw",
        "shortDescription": "This code example gives an out of box demonstration of the OPA module on the Q41 family of devices.",
        "ide": {
                  "name": "MPLABX",
                  "semverRange": ">=5.40.0"
              },
              "compiler": [
      			{
      				"name": "XC8",
      				"semverRange": "^2.20.0"
      			}
      		],
              "dfp": {
                  "name": "PIC18F-Q_DFP",
                  "semverRange": "^1.5.124"
              },
              "configurator": {
                  "name": "MCC",
                  "semverRange": ">=3.95.0"
              },
              "device": {
                  "metaDataVersion": "1.0.0",
                  "category": "com.microchip.portal.contentRef",
                  "content": {
                      "metaDataVersion": "1.0.0",
                      "category": "com.microchip.device",
                      "name": "PIC18F16Q41",
                      "versionRange": "*"
                  }
              },
              "author": "Microchip",
              "subcategories": [
                  "MCC",
                  [
                     "Peripherals", "OPA"
                  ],
                  [
                     "Peripherals", "UART"
                  ],
                  [
                     "Peripherals", "TMR2"
                  ],
                  [
                     "Peripherals", "CLC"
                  ]				  
              ],
              "peripherals": [
                  "OPA","UART","TMR2","CLC"
              ],
        "keywords": [
            "MCC",
            "Intelligent Analog",
            "Core Independent",
            "Sensor",
            "Operational Amplifier"
        ],
		"additionalData": {
			"longDescription": {
				"metaDataVersion": "1.0.0",
				"category": "com.microchip.portal.fileRef",
				"content": {
					"metaDataVersion": "1.0.0",
					"fileName": "./README.md",
					"mimeType": "text/markdown"
				}
			}
		}
	}
}
